[{"content":"testing 3\nSome third party entries in your sources.list were disabled. You can\nre-enable them after the upgrade with the \u0026lsquo;software-properties\u0026rsquo; tool\nor your package manager.\n","description":"","id":0,"section":"posts","tags":null,"title":"My third Post","uri":"http://ofsaleem.me/posts/test-post/"},{"content":"create the tracker with your public ip and port as the tracker url, but then once youre seeding, change the tracker url locally to your local ip. then it should connect.\n","description":"","id":1,"section":"posts","tags":null,"title":"embedded tracker","uri":"http://ofsaleem.me/posts/embedded-tracker/"},{"content":"i am a cow\ni am not a cat\nmoo im a cow\n","description":"","id":2,"section":"posts","tags":null,"title":"My First Post","uri":"http://ofsaleem.me/posts/my-first-post/"}]